{
  "id": "1318996753958522880",
  "author": "BMJ Global Health",
  "date": "2020-10-21T19:25:06.000Z",
  "text": "Lockdown measures in response to COVID-19 in nine sub-Saharan African countries \nhttps://gh.bmj.com/content/5/10/e003319\u2026",
  "tweet_url": "https://x.com/i/web/status/1318996753958522880",
  "image_url": "https://pbs.twimg.com/media/Ek4EjuSXEAAtjL2?format=jpg&name=small",
  "image_width": 680,
  "image_height": 546,
  "misleading": false,
  "errors": {
    "VisualizationDesignViolations": [],
    "ReasoningErrors": []
  }
}