{
  "id": "1428699498801414146",
  "author": "\ud835\udcdd\ud835\udcf8\ud835\udcfc\ud835\udcef\ud835\udcee\ud835\udcfb\ud835\udcea\ud835\udcfd\ud835\udcfe",
  "date": "2021-08-20T12:44:39.000Z",
  "text": "U.S. extends non-essential travel restrictions at land border with Canada until Sept. 21.\n Good thinking.",
  "tweet_url": "https://x.com/i/web/status/1428699498801414146",
  "image_url": "https://pbs.twimg.com/media/E9PCis3XMAIVjPV?format=png&name=small",
  "image_width": 680,
  "image_height": 492,
  "misleading": false,
  "errors": {
    "VisualizationDesignViolations": [],
    "ReasoningErrors": []
  }
}