{
  "id": "1269119840708521984",
  "author": "The Times Of India",
  "date": "2020-06-06T04:12:03.000Z",
  "text": "Tracking #Covid19 \n\n#CautionYesPanicNo #IndiaFightsCorona #CoronavirusOutbreak Live updates: http://toi.in/1nFnFZ",
  "tweet_url": "https://x.com/i/web/status/1269119840708521984",
  "image_url": "https://pbs.twimg.com/media/EZzRraBUYAASLHf?format=jpg&name=small",
  "image_width": 431,
  "image_height": 680,
  "misleading": true,
  "errors": {
    "VisualizationDesignViolations": [
      "Value as area/volume"
    ],
    "ReasoningErrors": []
  }
}