{
  "id": "1315433762566537218",
  "author": "Eric Topol",
  "date": "2020-10-11T23:27:03.000Z",
  "text": "Covid cases beget covid hospitalizations. Period.\nOn the upswing again. >34,000 today.\n\n@COVID19Tracking",
  "tweet_url": "https://x.com/i/web/status/1315433762566537218",
  "image_url": "https://pbs.twimg.com/media/EkFbqRRU4AAT6H_?format=jpg&name=small",
  "image_width": 680,
  "image_height": 372,
  "misleading": true,
  "errors": {
    "VisualizationDesignViolations": [
      "Dual axis"
    ],
    "ReasoningErrors": []
  }
}