{
  "id": "1240239038029799427",
  "author": "Alexandra Topping",
  "date": "2020-03-18T11:30:03.000Z",
  "text": "The global number of cases of confirmed #coronavirus cases has reached 200,000",
  "tweet_url": "https://x.com/i/web/status/1240239038029799427",
  "image_url": "https://pbs.twimg.com/media/ETY20OxXYAAd7QR?format=jpg&name=small",
  "image_width": 680,
  "image_height": 323,
  "misleading": true,
  "errors": {
    "VisualizationDesignViolations": [
      "Value as area/volume"
    ],
    "ReasoningErrors": []
  }
}