{
  "id": "1267752441317134338",
  "author": "Alistair Haimes",
  "date": "2020-06-02T09:38:30.000Z",
  "text": "UK: deaths at home in England & Wales.\n\nTotal since mid-March: covid-mentioned 1,969, covid not mentioned 12,459.",
  "tweet_url": "https://x.com/i/web/status/1267752441317134338",
  "image_url": "https://pbs.twimg.com/media/EZf15ZaWoAEEKi5?format=png&name=small",
  "image_width": 680,
  "image_height": 440,
  "misleading": true,
  "errors": {
    "VisualizationDesignViolations": [
      "Inappropriate encoding"
    ],
    "ReasoningErrors": [
      "Setting an arbitrary threshold"
    ]
  }
}