{
  "id": "1317186469757390849",
  "author": "National Department of Health",
  "date": "2020-10-16T19:31:41.000Z",
  "text": "16 October 2020 #COVID19 statistics in South Africa #CoronaVirusSA",
  "tweet_url": "https://x.com/i/web/status/1317186469757390849",
  "image_url": "https://pbs.twimg.com/media/EkeWGx6XEAE9yzL?format=jpg&name=900x900",
  "image_width": 643,
  "image_height": 900,
  "misleading": false,
  "errors": {
    "VisualizationDesignViolations": [],
    "ReasoningErrors": []
  }
}