{
  "id": "1312034883032608780",
  "author": "Prof. Shamika Ravi",
  "date": "2020-10-02T04:27:28.000Z",
  "text": "This is why #Punjab is a cause for concern. #COVID19India \n@drharshvardhan\n \n@capt_amarinder",
  "tweet_url": "https://x.com/i/web/status/1312034883032608780",
  "image_url": "https://pbs.twimg.com/media/EjVIFPaVgAsg4f1?format=jpg&name=small",
  "image_width": 680,
  "image_height": 599,
  "misleading": false,
  "errors": {
    "VisualizationDesignViolations": [],
    "ReasoningErrors": []
  }
}