{
  "id": "1375312587441639425",
  "author": "Vishwambhar N Mishra Varanasi",
  "date": "2021-03-26T05:04:07.000Z",
  "text": "Better to play #Holi within family members during #COVID19. #SafetyFirst",
  "tweet_url": "https://x.com/i/web/status/1375312587441639425",
  "image_url": "https://pbs.twimg.com/media/ExYXgY1VgAIVPWk?format=jpg&name=small",
  "image_width": 680,
  "image_height": 475,
  "misleading": true,
  "errors": {
    "VisualizationDesignViolations": [
      "Value as area/volume"
    ],
    "ReasoningErrors": []
  }
}